dbt_feature_flags/__init__.py
dbt_feature_flags/base.py
dbt_feature_flags/harness.py
dbt_feature_flags/launchdarkly.py
dbt_feature_flags/patch.py
zzz_dbt_feature_flags.pth
dbt_feature_flags-0.5.1.dist-info/LICENSE
dbt_feature_flags-0.5.1.dist-info/METADATA
dbt_feature_flags-0.5.1.dist-info/WHEEL
dbt_feature_flags-0.5.1.dist-info/RECORD
