Metadata-Version: 2.1
Name: dbt-feature-flags
Version: 0.5.1
Summary: Use feature flags in dbt models
Home-page: https://github.com/z3z1ma/dbt-feature-flags
Author: z3z1ma
Author-email: butler.alex2010@gmail.com
Requires-Python: >=3.8,<4
Classifier: Programming Language :: Python :: 3
Classifier: Programming Language :: Python :: 3.8
Classifier: Programming Language :: Python :: 3.9
Classifier: Programming Language :: Python :: 3.10
Classifier: Programming Language :: Python :: 3.11
Requires-Dist: dbt-core (>=1.0.0)
Requires-Dist: harness-featureflags (>=1.1.3,<2.0.0)
Requires-Dist: launchdarkly-server-sdk (>=7.5.1,<8.0.0)
Project-URL: Repository, https://github.com/z3z1ma/dbt-feature-flags
